ECE251/controller/controller.v


module controller(
    input clk,
    input [15:0] instruction,
    input [1:0] flags,
    output wire [7:0] pc,
    output wire be, rw, mmuxsel, je, re0, memwrite
);

reg bufenable, regwrite, muxsel, jumpenable, ret0, writetomem;
reg [7:0] programcounter;

initial begin
    regwrite = 0;
    jumpenable = 0;
    muxsel = 0;
    writetomem = 0;
    ret0 = 0;
    bufenable = 0;
    programcounter = -1;
    #10;
end

always @(posedge clk ) begin

    if (instruction == 16'b0000000000000000) begin
        ret0 = 1;
    end
   case(instruction[15:12]) 
   4'b0000 : begin 
       case(instruction[11:9])
       3'b001 : jumpenable = 1;
       3'b010 : begin
           if(flags[1]==0) begin
               jumpenable = 1;
           end else begin
               jumpenable = 0;
           end
       end
       3'b011 : begin
           if(flags[1]==1) begin
               jumpenable = 1;
           end else begin
               jumpenable = 0;
           end
       end
       3'b100: begin 
           if(flags[0] == 0) begin
               jumpenable = 1;
           end else begin
               jumpenable = 1;
           end
       end
       3'b101: begin
           if(flags[0] == 1) begin
               jumpenable = 1;
           end else begin
               jumpenable = 1;
           end
       end
       endcase
   end
   4'b1110 : begin 
       muxsel <= 1;
       #2;
       bufenable <= 1;
       #2;
       regwrite <= 1;
       #2;
       regwrite = 0;
       bufenable = 0;
       muxsel = 0;
   end
   4'b1111 : begin
       writetomem = 1;
       #2;
       writetomem = 0;
   end
   4'b0001 : begin
       bufenable =  1;
       #2;
       regwrite = 1;
       #2;
       regwrite = 0;
       bufenable = 0;
   end
   4'b0010 : begin
       bufenable =  1;
       #2;
       regwrite = 1;
       #2;
       regwrite = 0;
       bufenable = 0;
   end
   4'b0011 : begin
       bufenable =  1;
       #2;
       regwrite = 1;
       #2;
       regwrite = 0;
       bufenable = 0;
   end
   4'b0100 : begin
       bufenable =  1;
       #2;
       regwrite = 1;
       #2;
       regwrite = 0;
       bufenable = 0;
   end
   4'b0101 : begin
       bufenable =  1;
       #2;
       regwrite = 1;
       #2;
       regwrite = 0;
       bufenable = 0;
   end
   4'b0110 : begin
       bufenable =  1;
       #2;
       regwrite = 1;
       #2;
       regwrite = 0;
       bufenable = 0;
   end
   4'b0111 : begin
       bufenable =  1;
       #2;
       regwrite = 1;
       #2;
       regwrite = 0;
       bufenable = 0;
   end
   4'b1000 : begin
       bufenable =  1;
       #2;
       regwrite = 1;
       #2;
       regwrite = 0;
       bufenable = 0;
   end
   4'b1001 : begin
       bufenable =  1;
       #2;
       regwrite = 1;
       #2;
       regwrite = 0;
       bufenable = 0;
   end
   4'b1010 : begin
       bufenable =  1;
       #2;
       regwrite = 1;
       #2;
       regwrite = 0;
       bufenable = 0;
   end
   4'b1011 : begin
       bufenable =  1;
       #2;
       regwrite = 1;
       #2;
       regwrite = 0;
       bufenable = 0;
   end
   4'b1100 : begin
       bufenable =  1;
       #2;
       regwrite = 1;
       #2;
       regwrite = 0;
       bufenable = 0;
   end
   4'b1101 : begin
       bufenable =  1;
       #2;
       regwrite = 1;
       #2;
       regwrite = 0;
       bufenable = 0;
   end
//    4'b1110 : begin
//        bufenable =  1;
//        #2;
//        regwrite = 1;
//        #2;
//        regwrite = 0;
//        bufenable = 0;
//    end
//    4'b1111 : begin
//        bufenable =  1;
//        #2;
//        regwrite = 1;
//        #2;
//        regwrite = 0;
//        bufenable = 0;
//    end
   default : begin
       bufenable  = 0;
       regwrite = 0;
   end
endcase
end

always @(posedge clk ) begin
  if( jumpenable == 1) begin
        programcounter = instruction[7:0];
        jumpenable = 0;
    end else if(jumpenable == 0) begin
        programcounter = programcounter + 1;
    end

    #20;
end

assign be = bufenable;
assign rw = regwrite;
assign mmuxsel = muxsel;
assign je = jumpenable;
assign re0 = ret0;
assign memwrite = writetomem;
assign pc = programcounter;


endmodule

ECE251/instruction/Imem.v

module Imem(
    input [7:0] inA,
    output wire [15:0] instruc
);

reg [15:0] ram [255:0];

initial $readmemb("program.txt", ram);


assign instruc = ram[inA];


endmodule

ECE251/instruction/ram.v

module ram(
    input [7:0] addr, datain,
    input we, clk,
    output wire [7:0] data
);

reg [7:0] ram [255:0];
reg [7:0] test;
initial begin
    ram[0] = 0;
    test = ram[addr];
end

always @(posedge clk ) begin
    if(we) begin
        ram[addr] = datain;
    end
end

assign data = ram[addr];


endmodule

ECE251/Mux2in1out/mux221.v
module mux2in1(
    input sel,
    input [7:0] inA, inB,
    output reg [7:0] out
);

always@(*) begin
    out = sel? inA : inB;
end

endmodule

ECE251/registerfile/regfile.v
module registers(
    input we,
    input [1:0] selwrite, outselA, outselB,
    input [1:0] flags,
    input [7:0] data,
    output wire [7:0] A, B,
    output wire [1:0] outflags
);

//reg [7:0] regifile [1:0];  //creates an 8 bit register with depth 8


reg [7:0] reg0, reg1, reg2, reg3; /* reg4, reg5, reg6, reg7, reg8;*/
reg [7:0] A1, B1;
reg [1:0] holdflag;
reg [7:0] test;

initial begin
    reg0 = 0;
    reg1 = 0;
    reg2 = 0;
    reg3 = 0;
    //regifile[2'b10] = 0;
    //regifile[2'b11] = 0;
end

always @(*) begin
    // if(regifile[3'b000] != 0) begin
    //     regifile[3'b000] = 0;
    // end
    if(we) begin
        case(selwrite)
        2'd0 : reg0 = data;
        2'd1 : reg1 = data;
        2'd2 : reg2 = data;
        2'd3 : reg3 = data;
        endcase
    end
end

//test = regifile[selwrite];

always @(*)begin
    if(~we)begin
        holdflag = flags;
        case(outselA)
        2'd0 : A1 = reg0;
        2'd1 : A1 = reg1;
        2'd2 : A1 = reg2;
        2'd3 : A1 = reg3;
        endcase
        case(outselB)
        2'd0 : B1= reg0;
        2'd1 : B1= reg1;
        2'd2 : B1= reg2;
        2'd3 : B1= reg3;
        endcase
    end

end

assign A = A1;
assign B = B1;
assign outflags = holdflag;

endmodule

ECE251/Buffer/8bitbuffer.v
module buffer8bit(
    input [7:0] in1,
    input enable,
    output reg [7:0] hold
);

always@(*)begin
    hold = enable ? in1 : 8'bzzzzzzzz;
end

endmodule

ECE251/ALU/ALU.v
`define NOT 3'b000
`define AND 3'b001
`define OR 3'b010
`define MUL_CMPI 3'b011
`define ADD 3'b100
`define SUB 3'b101
`define SIX 3'b110
`define SVN 3'b111

module ALU(
    input [3:0] opcase,
    input [2:0] shiftamt,
    input [7:0] A, B,
    output reg [7:0] out1,
    output wire [1:0] flags 
);
    reg [1:0] cmpflag;
    reg [7:0] cmpreg;
    always@(*)begin
        case(opcase[2:0])
        `NOT : out1 = ~A;
        `AND : out1 = A&B;
        `OR : out1 = A | B;
        `ADD : out1 = A + B;   
        `SUB : out1 = A + (~B + 8'b00000001);     // A SUB B -> A ADD (-B)
        default : out1 = 8'bzzzzzzzz;
        endcase

        if(opcase[3] == 0) begin
            case(opcase[2:0])
            `MUL_CMPI : out1 = A*B;
            `SIX : out1 = A >> shiftamt;
            `SVN : out1 = A << shiftamt; 
            endcase
        end

        if(opcase[3] == 1) begin
            case(opcase[2:0])
            `MUL_CMPI : begin
                out1 = 8'bzzzzzzzz;
                cmpreg = A - B;
                cmpflag[1] = (A>B);
                cmpflag[0] = (cmpreg == 8'b00000000);
            end
            endcase
        end
    end


    assign flags[1] = cmpflag;  // Zero

endmodule

ECE251/decoder/decoder.v
// Based on UCDAVIS example decoder files :https://www.ece.ucdavis.edu/~bbaas/281/notes/Handout.verilog6.pdf

module insdecoder(
    input [15:0] instruction,
    output [3:0] opcode,
    output [2:0] opcode2, shiftamt,
    output [1:0] Rm, Rs1, Rs2,
    output [7:0] constant
);

assign opcode = instruction[15:12];
assign Rm = instruction[11:10];
assign Rs1 = instruction[9:8];
assign Rs2 = instruction[7:6];
assign shiftamt = instruction[5:3];
assign constant = instruction[7:0];
assign opcode2 = instruction[11:9];

endmodule

ECE251/cpu/cpu.v
`timescale 1ps/1ps

//bulk of computer lies in these include files
`include "../decoder/decoder.v"
`include "../instruction/imem.v"
`include "../mux2in1out/mux221.v"
`include "../ALU/ALU.v"
`include "../Buffer/8bitbuffer.v"
`include "../instruction/ram.v"
`include "../registerfile/regfile.v"
`include "../controller/controller.v"

module cpu();

//these are set to be wires so that they can be continously assigned
wire [15:0] instruction;
wire [3:0] opcode;
wire [2:0] opcode2, shiftamt;
wire [1:0] Rm, Rs1, Rs2;
wire [7:0] constant;
wire [7:0] outputofmem;
wire [7:0] regA, regB, alubuffer, data, databuffer, aluOut;
wire [1:0] aluflag, storedflag;
wire [7:0] pc;

reg clk;

//outputs for the controller that control the rest of the circuit
wire jumpenable, regwrite, writetomem, bufenable, muxsel, ret0;

insdecoder instrucdecoder(instruction, opcode, opcode2, shiftamt, Rm, Rs1, Rs2, constant);
ALU alu1(opcode, shiftamt, regA, alubuffer, aluOut, aluflag);
buffer8bit buf1(data, bufenable, databuffer);
registers regis(regwrite, Rm, Rs1, Rs2, aluflag, databuffer, regA, regB, storedflag);
mux2in1 memorymux(muxsel, outputofmem, aluOut, data);
mux2in1 immediatemux(opcode[3], constant, regB, alubuffer);
ram dataram256(constant, regA, writetomem, writetomem, outputofmem);
Imem instructionmemory(pc, instruction);
controller maincontroller(clk, instruction, storedflag, pc, bufenable, regwrite, muxsel, jumpenable, ret0, writetomem);


//inspired from the way that in c, programs usually end with a return 0 to show that they compiled properly.
//This is the return 0 of our ISA
always @(posedge clk ) begin
    if(ret0 == 1) begin
        $finish;
    end

end

//clock signal
initial begin
clk = 0;
end

always begin
    #10;
    clk = ~clk;
end

initial begin
    $dumpfile("cpu.vcd");

    //testing purposes
    //$dumpvars(0, pc, jumpenable, clk, ret0, opcode, opcode2, shiftamt, Rm, Rs1, Rs2, constant, instruction, regis);
    $dumpvars(0, cpu);



    $display("finish");
end


endmodule

ECE251/cpu/cpu.vcd
$date
	Sat May 14 16:10:55 2022
$end
$version
	Icarus Verilog
$end
$timescale
	1ps
$end
$scope module cpu $end
$var wire 1 ! writetomem $end
$var wire 2 " storedflag [1:0] $end
$var wire 3 # shiftamt [2:0] $end
$var wire 1 $ ret0 $end
$var wire 1 % regwrite $end
$var wire 8 & regB [7:0] $end
$var wire 8 ' regA [7:0] $end
$var wire 8 ( pc [7:0] $end
$var wire 8 ) outputofmem [7:0] $end
$var wire 3 * opcode2 [2:0] $end
$var wire 4 + opcode [3:0] $end
$var wire 1 , muxsel $end
$var wire 1 - jumpenable $end
$var wire 16 . instruction [15:0] $end
$var wire 8 / databuffer [7:0] $end
$var wire 8 0 data [7:0] $end
$var wire 8 1 constant [7:0] $end
$var wire 1 2 bufenable $end
$var wire 2 3 aluflag [1:0] $end
$var wire 8 4 alubuffer [7:0] $end
$var wire 8 5 aluOut [7:0] $end
$var wire 2 6 Rs2 [1:0] $end
$var wire 2 7 Rs1 [1:0] $end
$var wire 2 8 Rm [1:0] $end
$var reg 1 9 clk $end
$scope module alu1 $end
$var wire 2 : flags [1:0] $end
$var wire 3 ; shiftamt [2:0] $end
$var wire 4 < opcase [3:0] $end
$var wire 8 = B [7:0] $end
$var wire 8 > A [7:0] $end
$var reg 2 ? cmpflag [1:0] $end
$var reg 8 @ cmpreg [7:0] $end
$var reg 8 A out1 [7:0] $end
$upscope $end
$scope module buf1 $end
$var wire 8 B in1 [7:0] $end
$var wire 1 2 enable $end
$var reg 8 C hold [7:0] $end
$upscope $end
$scope module dataram256 $end
$var wire 8 D data [7:0] $end
$var wire 1 ! we $end
$var wire 8 E datain [7:0] $end
$var wire 1 ! clk $end
$var wire 8 F addr [7:0] $end
$var reg 8 G test [7:0] $end
$upscope $end
$scope module immediatemux $end
$var wire 1 H sel $end
$var wire 8 I inB [7:0] $end
$var wire 8 J inA [7:0] $end
$var reg 8 K out [7:0] $end
$upscope $end
$scope module instrucdecoder $end
$var wire 3 L shiftamt [2:0] $end
$var wire 3 M opcode2 [2:0] $end
$var wire 4 N opcode [3:0] $end
$var wire 16 O instruction [15:0] $end
$var wire 8 P constant [7:0] $end
$var wire 2 Q Rs2 [1:0] $end
$var wire 2 R Rs1 [1:0] $end
$var wire 2 S Rm [1:0] $end
$upscope $end
$scope module instructionmemory $end
$var wire 16 T instruc [15:0] $end
$var wire 8 U inA [7:0] $end
$upscope $end
$scope module maincontroller $end
$var wire 1 2 be $end
$var wire 1 9 clk $end
$var wire 16 V instruction [15:0] $end
$var wire 1 - je $end
$var wire 1 ! memwrite $end
$var wire 1 , mmuxsel $end
$var wire 1 $ re0 $end
$var wire 1 % rw $end
$var wire 8 W pc [7:0] $end
$var wire 2 X flags [1:0] $end
$var reg 1 Y bufenable $end
$var reg 1 Z jumpenable $end
$var reg 1 [ muxsel $end
$var reg 8 \ programcounter [7:0] $end
$var reg 1 ] regwrite $end
$var reg 1 ^ ret0 $end
$var reg 1 _ writetomem $end
$upscope $end
$scope module memorymux $end
$var wire 8 ` inA [7:0] $end
$var wire 8 a inB [7:0] $end
$var wire 1 , sel $end
$var reg 8 b out [7:0] $end
$upscope $end
$scope module regis $end
$var wire 8 c A [7:0] $end
$var wire 8 d B [7:0] $end
$var wire 8 e data [7:0] $end
$var wire 2 f flags [1:0] $end
$var wire 2 g outflags [1:0] $end
$var wire 2 h outselA [1:0] $end
$var wire 2 i outselB [1:0] $end
$var wire 2 j selwrite [1:0] $end
$var wire 1 % we $end
$var reg 8 k A1 [7:0] $end
$var reg 8 l B1 [7:0] $end
$var reg 2 m holdflag [1:0] $end
$var reg 8 n reg0 [7:0] $end
$var reg 8 o reg1 [7:0] $end
$var reg 8 p reg2 [7:0] $end
$var reg 8 q reg3 [7:0] $end
$upscope $end
$upscope $end
$enddefinitions $end
#0
$dumpvars
b0 q
b0 p
b0 o
b0 n
bx m
b0 l
b0 k
b0 j
b0 i
b0 h
bx g
bx f
bz e
b0 d
b0 c
b11111111 b
b11111111 a
b0 `
0_
0^
0]
b11111111 \
0[
0Z
0Y
bx X
b11111111 W
b0 V
b11111111 U
b0 T
b0 S
b0 R
b0 Q
b0 P
b0 O
b0 N
b0 M
b0 L
b0 K
b0 J
b0 I
0H
bx G
b0 F
b0 E
b0 D
bz C
b11111111 B
b11111111 A
bx @
bx ?
b0 >
b0 =
b0 <
b0 ;
bx :
09
b0 8
b0 7
b0 6
b11111111 5
b0 4
bx 3
02
b0 1
b11111111 0
bz /
b0 .
0-
0,
b0 +
b0 *
b0 )
b11111111 (
b0 '
b0 &
0%
0$
b0 #
bx "
0!
$end
#10
b101 0
b101 B
b101 b
b101 4
b101 =
b101 K
1H
b101 5
b101 A
b101 a
b101 /
b101 C
b101 e
b10 *
b10 M
bx )
bx D
bx `
b101 1
b101 F
b101 J
b101 P
b1 8
b1 S
b1 j
b1100 +
b1100 <
b1100 N
12
1Y
b1100010000000101 .
b1100010000000101 O
b1100010000000101 T
b1100010000000101 V
b0 (
b0 U
b0 W
b0 \
19
#12
b101 o
1%
1]
#14
bz /
bz C
bz e
02
0Y
0%
0]
#20
09
#30
b1 0
b1 B
b1 b
b1 5
b1 A
b1 a
b1 4
b1 =
b1 K
b1 /
b1 C
b1 e
b100 *
b100 M
b1 1
b1 F
b1 J
b1 P
b10 8
b10 S
b10 j
12
1Y
b1100100000000001 .
b1100100000000001 O
b1100100000000001 T
b1100100000000001 V
b1 (
b1 U
b1 W
b1 \
19
#32
b1 p
1%
1]
#34
bz /
bz C
bz e
02
0Y
0%
0]
#40
09
#50
b101 0
b101 B
b101 b
b1 &
b1 I
b1 d
b1 l
b101 '
b101 >
b101 E
b101 c
b101 k
0H
b101 5
b101 A
b101 a
b101 /
b101 C
b101 e
b10000000 1
b10000000 F
b10000000 J
b10000000 P
b10 6
b10 Q
b10 i
b1 7
b1 R
b1 h
b11 +
b11 <
b11 N
12
1Y
b11100110000000 .
b11100110000000 O
b11100110000000 T
b11100110000000 V
b10 (
b10 U
b10 W
b10 \
19
#52
b11001 /
b11001 C
b11001 e
b11001 0
b11001 B
b11001 b
b11001 5
b11001 A
b11001 a
b101 4
b101 =
b101 K
b101 &
b101 I
b101 d
b101 l
b101 p
1%
1]
#54
bz /
bz C
bz e
02
0Y
0%
0]
#60
09
#70
b100 0
b100 B
b100 b
b1 4
b1 =
b1 K
b0 &
b0 I
b0 d
b0 l
1H
b100 5
b100 A
b100 a
b100 /
b100 C
b100 e
b10 *
b10 M
b1 1
b1 F
b1 J
b1 P
b0 6
b0 Q
b0 i
b1 8
b1 S
b1 j
b1101 +
b1101 <
b1101 N
12
1Y
b1101010100000001 .
b1101010100000001 O
b1101010100000001 T
b1101010100000001 V
b11 (
b11 U
b11 W
b11 \
19
#72
b11 /
b11 C
b11 e
b11 0
b11 B
b11 b
b11 5
b11 A
b11 a
b100 '
b100 >
b100 E
b100 c
b100 k
b100 o
1%
1]
#74
bz /
bz C
bz e
02
0Y
0%
0]
#80
09
#90
b11 "
b11 X
b11 g
b11 m
bz 0
bz B
bz b
b11 3
b11 :
b11 f
b11 ?
b1 @
bz 5
bz A
bz a
bz /
bz C
bz e
b0 *
b0 M
b0 8
b0 S
b0 j
b1011 +
b1011 <
b1011 N
12
1Y
b1011000100000001 .
b1011000100000001 O
b1011000100000001 T
b1011000100000001 V
b100 (
b100 U
b100 W
b100 \
19
#92
bz &
bz I
bz d
bz l
bz n
1%
1]
#94
02
0Y
0%
0]
#100
09
#110
b11111010 0
b11111010 B
b11111010 b
bz 4
bz =
bz K
b101 '
b101 >
b101 E
b101 c
b101 k
0H
b11111010 5
b11111010 A
b11111010 a
b11 *
b11 M
b10 1
b10 F
b10 J
b10 P
b10 7
b10 R
b10 h
b1 8
b1 S
b1 j
b0 +
b0 <
b0 N
1-
1Z
b11000000010 .
b11000000010 O
b11000000010 T
b11000000010 V
b101 (
b101 U
b101 W
b101 \
19
#120
09
#130
b10100 0
b10100 B
b10100 b
b101 4
b101 =
b101 K
b101 &
b101 I
b101 d
b101 l
b100 '
b100 >
b100 E
b100 c
b100 k
b10100 5
b10100 A
b10100 a
b10100 /
b10100 C
b10100 e
b100 *
b100 M
b10000000 1
b10000000 F
b10000000 J
b10000000 P
b10 6
b10 Q
b10 i
b1 7
b1 R
b1 h
b10 8
b10 S
b10 j
b11 +
b11 <
b11 N
12
1Y
0-
0Z
b11100110000000 .
b11100110000000 O
b11100110000000 T
b11100110000000 V
b10 (
b10 U
b10 W
b10 \
19
#132
b1010000 /
b1010000 C
b1010000 e
b1010000 0
b1010000 B
b1010000 b
b1010000 5
b1010000 A
b1010000 a
b10100 4
b10100 =
b10100 K
b10100 &
b10100 I
b10100 d
b10100 l
b10100 p
1%
1]
#134
bz /
bz C
bz e
02
0Y
0%
0]
#140
09
#150
b11 0
b11 B
b11 b
b1 4
b1 =
b1 K
bz &
bz I
bz d
bz l
1H
b11 5
b11 A
b11 a
b11 /
b11 C
b11 e
b10 *
b10 M
b1 1
b1 F
b1 J
b1 P
b0 6
b0 Q
b0 i
b1 8
b1 S
b1 j
b1101 +
b1101 <
b1101 N
12
1Y
b1101010100000001 .
b1101010100000001 O
b1101010100000001 T
b1101010100000001 V
b11 (
b11 U
b11 W
b11 \
19
#152
b10 /
b10 C
b10 e
b10 0
b10 B
b10 b
b10 5
b10 A
b10 a
b11 '
b11 >
b11 E
b11 c
b11 k
b11 o
1%
1]
#154
bz /
bz C
bz e
02
0Y
0%
0]
#160
09
#170
bz 0
bz B
bz b
b1 @
bz 5
bz A
bz a
bz /
bz C
bz e
b0 *
b0 M
b0 8
b0 S
b0 j
b1011 +
b1011 <
b1011 N
12
1Y
b1011000100000001 .
b1011000100000001 O
b1011000100000001 T
b1011000100000001 V
b100 (
b100 U
b100 W
b100 \
19
#172
1%
1]
#174
02
0Y
0%
0]
#180
09
#190
b11101011 0
b11101011 B
b11101011 b
bz 4
bz =
bz K
b10100 '
b10100 >
b10100 E
b10100 c
b10100 k
0H
b11101011 5
b11101011 A
b11101011 a
b11 *
b11 M
b10 1
b10 F
b10 J
b10 P
b10 7
b10 R
b10 h
b1 8
b1 S
b1 j
b0 +
b0 <
b0 N
1-
1Z
b11000000010 .
b11000000010 O
b11000000010 T
b11000000010 V
b101 (
b101 U
b101 W
b101 \
19
#200
09
#210
b111100 0
b111100 B
b111100 b
b10100 4
b10100 =
b10100 K
b10100 &
b10100 I
b10100 d
b10100 l
b11 '
b11 >
b11 E
b11 c
b11 k
b111100 5
b111100 A
b111100 a
b111100 /
b111100 C
b111100 e
b100 *
b100 M
b10000000 1
b10000000 F
b10000000 J
b10000000 P
b10 6
b10 Q
b10 i
b1 7
b1 R
b1 h
b10 8
b10 S
b10 j
b11 +
b11 <
b11 N
12
1Y
0-
0Z
b11100110000000 .
b11100110000000 O
b11100110000000 T
b11100110000000 V
b10 (
b10 U
b10 W
b10 \
19
#212
b10110100 /
b10110100 C
b10110100 e
b10110100 0
b10110100 B
b10110100 b
b10110100 5
b10110100 A
b10110100 a
b111100 4
b111100 =
b111100 K
b111100 &
b111100 I
b111100 d
b111100 l
b111100 p
1%
1]
#214
bz /
bz C
bz e
02
0Y
0%
0]
#220
09
#230
b10 0
b10 B
b10 b
b1 4
b1 =
b1 K
bz &
bz I
bz d
bz l
1H
b10 5
b10 A
b10 a
b10 /
b10 C
b10 e
b10 *
b10 M
b1 1
b1 F
b1 J
b1 P
b0 6
b0 Q
b0 i
b1 8
b1 S
b1 j
b1101 +
b1101 <
b1101 N
12
1Y
b1101010100000001 .
b1101010100000001 O
b1101010100000001 T
b1101010100000001 V
b11 (
b11 U
b11 W
b11 \
19
#232
b1 /
b1 C
b1 e
b1 0
b1 B
b1 b
b1 5
b1 A
b1 a
b10 '
b10 >
b10 E
b10 c
b10 k
b10 o
1%
1]
#234
bz /
bz C
bz e
02
0Y
0%
0]
#240
09
#250
bz 0
bz B
bz b
bz 5
bz A
bz a
bz /
bz C
bz e
b0 *
b0 M
b0 8
b0 S
b0 j
b1011 +
b1011 <
b1011 N
12
1Y
b1011000100000001 .
b1011000100000001 O
b1011000100000001 T
b1011000100000001 V
b100 (
b100 U
b100 W
b100 \
19
#252
1%
1]
#254
02
0Y
0%
0]
#260
09
#270
b11000011 0
b11000011 B
b11000011 b
bz 4
bz =
bz K
b111100 '
b111100 >
b111100 E
b111100 c
b111100 k
0H
b11000011 5
b11000011 A
b11000011 a
b11 *
b11 M
b10 1
b10 F
b10 J
b10 P
b10 7
b10 R
b10 h
b1 8
b1 S
b1 j
b0 +
b0 <
b0 N
1-
1Z
b11000000010 .
b11000000010 O
b11000000010 T
b11000000010 V
b101 (
b101 U
b101 W
b101 \
19
#280
09
#290
b1111000 0
b1111000 B
b1111000 b
b111100 4
b111100 =
b111100 K
b111100 &
b111100 I
b111100 d
b111100 l
b10 '
b10 >
b10 E
b10 c
b10 k
b1111000 5
b1111000 A
b1111000 a
b1111000 /
b1111000 C
b1111000 e
b100 *
b100 M
b10000000 1
b10000000 F
b10000000 J
b10000000 P
b10 6
b10 Q
b10 i
b1 7
b1 R
b1 h
b10 8
b10 S
b10 j
b11 +
b11 <
b11 N
12
1Y
0-
0Z
b11100110000000 .
b11100110000000 O
b11100110000000 T
b11100110000000 V
b10 (
b10 U
b10 W
b10 \
19
#292
b11110000 /
b11110000 C
b11110000 e
b11110000 0
b11110000 B
b11110000 b
b11110000 5
b11110000 A
b11110000 a
b1111000 4
b1111000 =
b1111000 K
b1111000 &
b1111000 I
b1111000 d
b1111000 l
b1111000 p
1%
1]
#294
bz /
bz C
bz e
02
0Y
0%
0]
#300
09
#310
b1 0
b1 B
b1 b
b1 4
b1 =
b1 K
bz &
bz I
bz d
bz l
1H
b1 5
b1 A
b1 a
b1 /
b1 C
b1 e
b10 *
b10 M
b1 1
b1 F
b1 J
b1 P
b0 6
b0 Q
b0 i
b1 8
b1 S
b1 j
b1101 +
b1101 <
b1101 N
12
1Y
b1101010100000001 .
b1101010100000001 O
b1101010100000001 T
b1101010100000001 V
b11 (
b11 U
b11 W
b11 \
19
#312
b0 /
b0 C
b0 e
b0 0
b0 B
b0 b
b0 5
b0 A
b0 a
b1 '
b1 >
b1 E
b1 c
b1 k
b1 o
1%
1]
#314
bz /
bz C
bz e
02
0Y
0%
0]
#320
09
#330
b0 "
b0 X
b0 g
b0 m
bz 0
bz B
bz b
b0 3
b0 :
b0 f
b0 ?
b0 @
bz 5
bz A
bz a
bz /
bz C
bz e
b0 *
b0 M
b0 8
b0 S
b0 j
b1011 +
b1011 <
b1011 N
12
1Y
b1011000100000001 .
b1011000100000001 O
b1011000100000001 T
b1011000100000001 V
b100 (
b100 U
b100 W
b100 \
19
#332
1%
1]
#334
02
0Y
0%
0]
#340
09
#350
b10000111 0
b10000111 B
b10000111 b
bz 4
bz =
bz K
b1111000 '
b1111000 >
b1111000 E
b1111000 c
b1111000 k
0H
b10000111 5
b10000111 A
b10000111 a
b11 *
b11 M
b10 1
b10 F
b10 J
b10 P
b10 7
b10 R
b10 h
b1 8
b1 S
b1 j
b0 +
b0 <
b0 N
b11000000010 .
b11000000010 O
b11000000010 T
b11000000010 V
b101 (
b101 U
b101 W
b101 \
19
#360
09
#370
bz 0
bz B
bz b
b1 4
b1 =
b1 K
bz '
bz >
bz E
bz c
bz k
1H
bz 5
bz A
bz a
b1111000 )
b1111000 D
b1111000 `
b100 *
b100 M
b1 1
b1 F
b1 J
b1 P
b0 7
b0 R
b0 h
b10 8
b10 S
b10 j
b1111 +
b1111 <
b1111 N
1!
1_
b1111100000000001 .
b1111100000000001 O
b1111100000000001 T
b1111100000000001 V
b110 (
b110 U
b110 W
b110 \
19
#372
0!
0_
#380
09
#390
b1111000 0
b1111000 B
b1111000 b
1,
1[
b110 *
b110 M
b11 8
b11 S
b11 j
b1110 +
b1110 <
b1110 N
b1110110000000001 .
b1110110000000001 O
b1110110000000001 T
b1110110000000001 V
b111 (
b111 U
b111 W
b111 \
19
#392
b1111000 /
b1111000 C
b1111000 e
12
1Y
#394
b1111000 q
1%
1]
#396
bz 0
bz B
bz b
bz /
bz C
bz e
0,
0[
02
0Y
0%
0]
#400
09
#410
bx 0
bx B
bx b
bz 4
bz =
bz K
0H
bx 5
bx A
bx a
b0 *
b0 M
b0 )
b0 D
b0 `
b0 1
b0 F
b0 J
b0 P
b0 8
b0 S
b0 j
b0 +
b0 <
b0 N
1$
1^
b0 .
b0 O
b0 T
b0 V
b1000 (
b1000 U
b1000 W
b1000 \
19
